afh_dl/__init__.py
afh_dl-1.0.3.dist-info/DESCRIPTION.rst
afh_dl-1.0.3.dist-info/METADATA
afh_dl-1.0.3.dist-info/RECORD
afh_dl-1.0.3.dist-info/WHEEL
afh_dl-1.0.3.dist-info/entry_points.txt
afh_dl-1.0.3.dist-info/metadata.json
afh_dl-1.0.3.dist-info/top_level.txt
