Metadata-Version: 2.0
Name: afh-dl
Version: 1.0.3
Summary: A command-line tool for downloading files from AndroidFileHost.
Home-page: https://github.com/kade-robertson/afh-dl
Author: Kade Robertson
Author-email: kade@kaderobertson.pw
License: MIT
Keywords: android file host downloader
Platform: UNKNOWN
Classifier: Development Status :: 3 - Alpha
Classifier: Intended Audience :: Developers
Classifier: Intended Audience :: End Users/Desktop
Classifier: License :: OSI Approved :: MIT License
Classifier: Operating System :: OS Independent
Classifier: Programming Language :: Python :: 2.7
Classifier: Programming Language :: Python :: 3
Classifier: Programming Language :: Python :: 3.0
Classifier: Programming Language :: Python :: 3.1
Classifier: Programming Language :: Python :: 3.2
Classifier: Programming Language :: Python :: 3.3
Classifier: Programming Language :: Python :: 3.4
Classifier: Programming Language :: Python :: 3.5
Classifier: Programming Language :: Python :: 3.6
Requires-Python: >=2.7, <4
Requires-Dist: future
Requires-Dist: requests
Requires-Dist: humanize
Requires-Dist: clint
